README.md
setup.py
global_cache/__init__.py
global_cache/utils_global_cache.py
global_cache/utils_persistence.py
global_messaging/__init__.py
global_messaging/utils_messaging.py
ubidots_global_cache.egg-info/PKG-INFO
ubidots_global_cache.egg-info/SOURCES.txt
ubidots_global_cache.egg-info/dependency_links.txt
ubidots_global_cache.egg-info/not-zip-safe
ubidots_global_cache.egg-info/requires.txt
ubidots_global_cache.egg-info/top_level.txt