Metadata-Version: 1.0
Name: ubidots-global-cache
Version: 0.0.4
Summary: The Ubidots Global Cache
Home-page: https://github.com/jdavidagudelo/global-cache.git
Author: jdavidagudelo
Author-email: jdaaa2009@gmail.com
License: MIT
Platform: UNKNOWN
